preconfig/__init__.py
preconfig/preconfig.py
preconfig-1.0.0.dist-info/METADATA
preconfig-1.0.0.dist-info/WHEEL
preconfig-1.0.0.dist-info/top_level.txt
preconfig-1.0.0.dist-info/RECORD
