Metadata-Version: 2.1
Name: preconfig
Version: 1.0.0
Summary: docker compose helper
Home-page: UNKNOWN
Author: jaytrairat
Author-email: <jay.trairat@gmail.com>
License: UNKNOWN
Keywords: jaytrairat
Platform: UNKNOWN
Classifier: Programming Language :: Python :: 3
